CHANGES.txt
README.txt
setup.py
src/z3c/__init__.py
src/z3c.recipe.scripts.egg-info/PKG-INFO
src/z3c.recipe.scripts.egg-info/SOURCES.txt
src/z3c.recipe.scripts.egg-info/dependency_links.txt
src/z3c.recipe.scripts.egg-info/entry_points.txt
src/z3c.recipe.scripts.egg-info/namespace_packages.txt
src/z3c.recipe.scripts.egg-info/not-zip-safe
src/z3c.recipe.scripts.egg-info/requires.txt
src/z3c.recipe.scripts.egg-info/top_level.txt
src/z3c/recipe/__init__.py
src/z3c/recipe/scripts/README.txt
src/z3c/recipe/scripts/__init__.py
src/z3c/recipe/scripts/scripts.py
src/z3c/recipe/scripts/tests.py