Metadata-Version: 1.0
Name: z3c.recipe.scripts
Version: 1.0.0b1
Summary: Recipe for installing Python scripts
Home-page: http://cheeseshop.python.org/pypi/z3c.recipe.scripts
Author: Gary Poster
Author-email: gary.poster@canonical.com
License: ZPL 2.1
Keywords: development build
Platform: UNKNOWN
Classifier: Development Status :: 5 - Production/Stable
Classifier: Framework :: Buildout
Classifier: Intended Audience :: Developers
Classifier: License :: OSI Approved :: Zope Public License
Classifier: Topic :: Software Development :: Build Tools
Classifier: Topic :: Software Development :: Libraries :: Python Modules
